{
"meta":{"test_sets":[],"test_metrics":[],"learn_metrics":[{"best_value":"Min","name":"RMSE"}],"launch_mode":"Train","parameters":"","iteration_count":100,"learn_sets":["learn"],"name":"experiment"},
"iterations":[
{"learn":[14.005006],"iteration":0,"passed_time":0.0007353145888,"remaining_time":0.07279614429},
{"learn":[13.14441192],"iteration":1,"passed_time":0.001565799561,"remaining_time":0.07672417848},
{"learn":[12.34258257],"iteration":2,"passed_time":0.002440816946,"remaining_time":0.07891974794},
{"learn":[11.64527793],"iteration":3,"passed_time":0.003005021493,"remaining_time":0.07212051584},
{"learn":[11.02766183],"iteration":4,"passed_time":0.003725072429,"remaining_time":0.07077637615},
{"learn":[10.43485794],"iteration":5,"passed_time":0.004287538894,"remaining_time":0.06717144268},
{"learn":[9.890641275],"iteration":6,"passed_time":0.00497102615,"remaining_time":0.06604363314},
{"learn":[9.492161212],"iteration":7,"passed_time":0.005712445347,"remaining_time":0.0656931215},
{"learn":[9.105082953],"iteration":8,"passed_time":0.006377232117,"remaining_time":0.06448090252},
{"learn":[8.674157135],"iteration":9,"passed_time":0.00706815929,"remaining_time":0.06361343361},
{"learn":[8.341743544],"iteration":10,"passed_time":0.007617358432,"remaining_time":0.06163135459},
{"learn":[8.049372916],"iteration":11,"passed_time":0.008233828623,"remaining_time":0.0603814099},
{"learn":[7.757318612],"iteration":12,"passed_time":0.008752614657,"remaining_time":0.0585751904},
{"learn":[7.522206899],"iteration":13,"passed_time":0.009298969278,"remaining_time":0.05712223985},
{"learn":[7.297756655],"iteration":14,"passed_time":0.01004313064,"remaining_time":0.05691107365},
{"learn":[7.088359431],"iteration":15,"passed_time":0.01054106065,"remaining_time":0.05534056841},
{"learn":[6.882113791],"iteration":16,"passed_time":0.01105582133,"remaining_time":0.05397842178},
{"learn":[6.704728832],"iteration":17,"passed_time":0.01163217254,"remaining_time":0.05299100825},
{"learn":[6.563881962],"iteration":18,"passed_time":0.01237618986,"remaining_time":0.0527616515},
{"learn":[6.418790279],"iteration":19,"passed_time":0.01295017893,"remaining_time":0.05180071573},
{"learn":[6.315756953],"iteration":20,"passed_time":0.01382098664,"remaining_time":0.05199323544},
{"learn":[6.210157751],"iteration":21,"passed_time":0.01440400918,"remaining_time":0.05106875983},
{"learn":[6.115058449],"iteration":22,"passed_time":0.01508732254,"remaining_time":0.05050973197},
{"learn":[6.014819884],"iteration":23,"passed_time":0.01564046601,"remaining_time":0.04952814235},
{"learn":[5.93117229],"iteration":24,"passed_time":0.01669173707,"remaining_time":0.05007521122},
{"learn":[5.844857622],"iteration":25,"passed_time":0.01763423827,"remaining_time":0.05018975507},
{"learn":[5.771145213],"iteration":26,"passed_time":0.01832226311,"remaining_time":0.04953797063},
{"learn":[5.704018229],"iteration":27,"passed_time":0.01922453113,"remaining_time":0.04943450862},
{"learn":[5.665806474],"iteration":28,"passed_time":0.02000901854,"remaining_time":0.04898759712},
{"learn":[5.616500369],"iteration":29,"passed_time":0.0206540562,"remaining_time":0.04819279779},
{"learn":[5.558023666],"iteration":30,"passed_time":0.02127494599,"remaining_time":0.04735391203},
{"learn":[5.510080976],"iteration":31,"passed_time":0.02196235861,"remaining_time":0.04667001205},
{"learn":[5.468747792],"iteration":32,"passed_time":0.0226610356,"remaining_time":0.04600876925},
{"learn":[5.429275534],"iteration":33,"passed_time":0.02328034368,"remaining_time":0.04519125538},
{"learn":[5.402117324],"iteration":34,"passed_time":0.02395381375,"remaining_time":0.04448565411},
{"learn":[5.367635151],"iteration":35,"passed_time":0.02466093806,"remaining_time":0.04384166766},
{"learn":[5.345181232],"iteration":36,"passed_time":0.02533529707,"remaining_time":0.0431384788},
{"learn":[5.319151269],"iteration":37,"passed_time":0.02598385922,"remaining_time":0.04239471768},
{"learn":[5.296134146],"iteration":38,"passed_time":0.02656049143,"remaining_time":0.04154333275},
{"learn":[5.269629003],"iteration":39,"passed_time":0.02721094092,"remaining_time":0.04081641138},
{"learn":[5.251147059],"iteration":40,"passed_time":0.02788023922,"remaining_time":0.04012034424},
{"learn":[5.248003302],"iteration":41,"passed_time":0.02810173561,"remaining_time":0.0388071587},
{"learn":[5.232376509],"iteration":42,"passed_time":0.02859699737,"remaining_time":0.03790764768},
{"learn":[5.213524255],"iteration":43,"passed_time":0.02925466218,"remaining_time":0.0372332064},
{"learn":[5.189691584],"iteration":44,"passed_time":0.02987613006,"remaining_time":0.03651527007},
{"learn":[5.166052198],"iteration":45,"passed_time":0.03050759807,"remaining_time":0.0358132673},
{"learn":[5.140406659],"iteration":46,"passed_time":0.03152698189,"remaining_time":0.03555170298},
{"learn":[5.118929684],"iteration":47,"passed_time":0.03281870951,"remaining_time":0.03555360197},
{"learn":[5.108792602],"iteration":48,"passed_time":0.0335427967,"remaining_time":0.03491189044},
{"learn":[5.098141225],"iteration":49,"passed_time":0.03420653626,"remaining_time":0.03420653626},
{"learn":[5.085926393],"iteration":50,"passed_time":0.03494661588,"remaining_time":0.03357616036},
{"learn":[5.067816804],"iteration":51,"passed_time":0.03559520125,"remaining_time":0.03285710885},
{"learn":[5.049834901],"iteration":52,"passed_time":0.03636163404,"remaining_time":0.03224522264},
{"learn":[5.03838627],"iteration":53,"passed_time":0.03693675324,"remaining_time":0.03146464165},
{"learn":[5.033534248],"iteration":54,"passed_time":0.03738999825,"remaining_time":0.03059181675},
{"learn":[5.023726885],"iteration":55,"passed_time":0.03802132885,"remaining_time":0.02987390124},
{"learn":[5.01290392],"iteration":56,"passed_time":0.03871053263,"remaining_time":0.02920268251},
{"learn":[5.005569127],"iteration":57,"passed_time":0.03934207788,"remaining_time":0.02848909088},
{"learn":[4.989969032],"iteration":58,"passed_time":0.04004494418,"remaining_time":0.02782784257},
{"learn":[4.976762446],"iteration":59,"passed_time":0.04064811909,"remaining_time":0.02709874606},
{"learn":[4.967222715],"iteration":60,"passed_time":0.0412338966,"remaining_time":0.0263626552},
{"learn":[4.954407599],"iteration":61,"passed_time":0.04202544912,"remaining_time":0.02575753333},
{"learn":[4.942125056],"iteration":62,"passed_time":0.04299588329,"remaining_time":0.0252515505},
{"learn":[4.930230716],"iteration":63,"passed_time":0.04366569239,"remaining_time":0.02456195197},
{"learn":[4.921695642],"iteration":64,"passed_time":0.04426308396,"remaining_time":0.02383396829},
{"learn":[4.906405625],"iteration":65,"passed_time":0.04502733894,"remaining_time":0.02319590188},
{"learn":[4.894330248],"iteration":66,"passed_time":0.04584925623,"remaining_time":0.02258246949},
{"learn":[4.88211557],"iteration":67,"passed_time":0.0467264827,"remaining_time":0.02198893304},
{"learn":[4.877946398],"iteration":68,"passed_time":0.04775886659,"remaining_time":0.02145688209},
{"learn":[4.863182126],"iteration":69,"passed_time":0.04856504116,"remaining_time":0.02081358907},
{"learn":[4.84646533],"iteration":70,"passed_time":0.04934548569,"remaining_time":0.02015519838},
{"learn":[4.838014752],"iteration":71,"passed_time":0.05021770405,"remaining_time":0.01952910713},
{"learn":[4.82981137],"iteration":72,"passed_time":0.05106046742,"remaining_time":0.01888537836},
{"learn":[4.817094767],"iteration":73,"passed_time":0.0517902626,"remaining_time":0.01819657875},
{"learn":[4.808314151],"iteration":74,"passed_time":0.05251268373,"remaining_time":0.01750422791},
{"learn":[4.796235023],"iteration":75,"passed_time":0.0532115948,"remaining_time":0.01680366152},
{"learn":[4.784434534],"iteration":76,"passed_time":0.05390838113,"remaining_time":0.01610250345},
{"learn":[4.774402487],"iteration":77,"passed_time":0.0546117625,"remaining_time":0.01540331763},
{"learn":[4.76731896],"iteration":78,"passed_time":0.05525857709,"remaining_time":0.01468898885},
{"learn":[4.75934113],"iteration":79,"passed_time":0.05579721554,"remaining_time":0.01394930389},
{"learn":[4.754106378],"iteration":80,"passed_time":0.05640182906,"remaining_time":0.01323005867},
{"learn":[4.744002932],"iteration":81,"passed_time":0.05709096034,"remaining_time":0.01253216203},
{"learn":[4.731700554],"iteration":82,"passed_time":0.05781899991,"remaining_time":0.01184244577},
{"learn":[4.723284153],"iteration":83,"passed_time":0.05858053878,"remaining_time":0.01115819786},
{"learn":[4.712232782],"iteration":84,"passed_time":0.05930083706,"remaining_time":0.0104648536},
{"learn":[4.703046867],"iteration":85,"passed_time":0.0602414476,"remaining_time":0.009806747283},
{"learn":[4.698601855],"iteration":86,"passed_time":0.06095177513,"remaining_time":0.009107736514},
{"learn":[4.692429407],"iteration":87,"passed_time":0.0615805204,"remaining_time":0.008397343691},
{"learn":[4.675027364],"iteration":88,"passed_time":0.06240076832,"remaining_time":0.007712454512},
{"learn":[4.662368584],"iteration":89,"passed_time":0.06371939782,"remaining_time":0.007079933092},
{"learn":[4.646206172],"iteration":90,"passed_time":0.06450375967,"remaining_time":0.006379492714},
{"learn":[4.641245848],"iteration":91,"passed_time":0.0654198679,"remaining_time":0.005688684165},
{"learn":[4.633900435],"iteration":92,"passed_time":0.06608186416,"remaining_time":0.004973903754},
{"learn":[4.624738236],"iteration":93,"passed_time":0.06675354545,"remaining_time":0.004260864603},
{"learn":[4.612798287],"iteration":94,"passed_time":0.06746271821,"remaining_time":0.00355066938},
{"learn":[4.605222001],"iteration":95,"passed_time":0.06815492336,"remaining_time":0.002839788473},
{"learn":[4.601725912],"iteration":96,"passed_time":0.06902982749,"remaining_time":0.002134943118},
{"learn":[4.59722371],"iteration":97,"passed_time":0.06966371878,"remaining_time":0.001421708546},
{"learn":[4.580235665],"iteration":98,"passed_time":0.07036355385,"remaining_time":0.0007107429682},
{"learn":[4.57591791],"iteration":99,"passed_time":0.07108283099,"remaining_time":0}
]}